yai/__init__.py
yai/script.py
yai-0.0.1a1.dist-info/DESCRIPTION.rst
yai-0.0.1a1.dist-info/METADATA
yai-0.0.1a1.dist-info/RECORD
yai-0.0.1a1.dist-info/WHEEL
yai-0.0.1a1.dist-info/entry_points.txt
yai-0.0.1a1.dist-info/metadata.json
yai-0.0.1a1.dist-info/top_level.txt
